LXMF/Handlers.py
LXMF/LXMF.py
LXMF/LXMPeer.py
LXMF/LXMRouter.py
LXMF/LXMessage.py
LXMF/LXStamper.py
LXMF/__init__.py
LXMF/_version.py
RNS/Buffer.py
RNS/Channel.py
RNS/Destination.py
RNS/Identity.py
RNS/Link.py
RNS/Packet.py
RNS/Resolver.py
RNS/Resource.py
RNS/Reticulum.py
RNS/Transport.py
RNS/__init__.py
RNS/_version.py
RNS/Cryptography/AES.py
RNS/Cryptography/Ed25519.py
RNS/Cryptography/HKDF.py
RNS/Cryptography/HMAC.py
RNS/Cryptography/Hashes.py
RNS/Cryptography/PKCS7.py
RNS/Cryptography/Provider.py
RNS/Cryptography/Proxies.py
RNS/Cryptography/SHA256.py
RNS/Cryptography/SHA512.py
RNS/Cryptography/Token.py
RNS/Cryptography/X25519.py
RNS/Cryptography/__init__.py
RNS/Cryptography/aes/__init__.py
RNS/Cryptography/aes/aes128.py
RNS/Cryptography/aes/aes256.py
RNS/Cryptography/pure25519/__init__.py
RNS/Cryptography/pure25519/_ed25519.py
RNS/Cryptography/pure25519/basic.py
RNS/Cryptography/pure25519/ed25519_oop.py
RNS/Cryptography/pure25519/eddsa.py
RNS/Interfaces/AX25KISSInterface.py
RNS/Interfaces/AutoInterface.py
RNS/Interfaces/BackboneInterface.py
RNS/Interfaces/I2PInterface.py
RNS/Interfaces/Interface.py
RNS/Interfaces/KISSInterface.py
RNS/Interfaces/LocalInterface.py
RNS/Interfaces/PipeInterface.py
RNS/Interfaces/RNodeInterface.py
RNS/Interfaces/RNodeMultiInterface.py
RNS/Interfaces/SerialInterface.py
RNS/Interfaces/TCPInterface.py
RNS/Interfaces/UDPInterface.py
RNS/Interfaces/WeaveInterface.py
RNS/Interfaces/__init__.py
RNS/Interfaces/Android/KISSInterface.py
RNS/Interfaces/Android/RNodeInterface.py
RNS/Interfaces/Android/SerialInterface.py
RNS/Interfaces/Android/__init__.py
RNS/Interfaces/util/__init__.py
RNS/Interfaces/util/netinfo.py
RNS/Utilities/__init__.py
RNS/Utilities/rncp.py
RNS/Utilities/rnid.py
RNS/Utilities/rnir.py
RNS/Utilities/rnodeconf.py
RNS/Utilities/rnpath.py
RNS/Utilities/rnprobe.py
RNS/Utilities/rnsd.py
RNS/Utilities/rnstatus.py
RNS/Utilities/rnx.py
RNS/vendor/__init__.py
RNS/vendor/configobj.py
RNS/vendor/platformutils.py
RNS/vendor/umsgpack.py
sbapp-1.8.0.dist-info/licenses/LICENSE
sbapp-1.8.0.dist-info/METADATA
sbapp-1.8.0.dist-info/WHEEL
sbapp-1.8.0.dist-info/entry_points.txt
sbapp-1.8.0.dist-info/top_level.txt
sbapp-1.8.0.dist-info/RECORD
