Metadata-Version: 2.4
Name: sbapp
Version: 1.8.0
Summary: LXMF client for Android, Linux and macOS allowing you to communicate with people or LXMF-compatible systems over Reticulum networks using LoRa, Packet Radio, WiFi, I2P, or anything else Reticulum supports.
Home-page: https://unsigned.io/sideband
Author: Mark Qvist
Author-email: mark@unsigned.io
Classifier: Programming Language :: Python :: 3
Classifier: License :: Other/Proprietary License
Classifier: Operating System :: OS Independent
Requires-Python: >=3.7
License-File: LICENSE
Requires-Dist: rns>=1.0.1
Requires-Dist: lxmf>=0.9.1
Requires-Dist: kivy>=2.3.0
Requires-Dist: pillow>=10.2.0
Requires-Dist: qrcode
Requires-Dist: materialyoucolor>=2.0.7
Requires-Dist: ffpyplayer
Requires-Dist: sh
Requires-Dist: numpy>=2.0.0
Requires-Dist: lxst>=0.3.0
Requires-Dist: mistune>=3.0.2
Requires-Dist: beautifulsoup4
Requires-Dist: pycodec2>=4.1.0; sys_platform != "Windows" and sys_platform != "win32" and sys_platform != "darwin"
Requires-Dist: pyaudio; sys_platform == "linux"
Requires-Dist: pyobjus; sys_platform == "darwin"
Requires-Dist: pyogg; sys_platform == "Windows" and sys_platform != "win32"
Requires-Dist: audioop-lts>=0.2.1; python_version >= "3.13"
Dynamic: author
Dynamic: author-email
Dynamic: classifier
Dynamic: description
Dynamic: description-content-type
Dynamic: home-page
Dynamic: license-file
Dynamic: requires-dist
Dynamic: requires-python
Dynamic: summary
